[
  {
    "name": "Bobslæde",
    "description": "Some gems have hidden qualities beyond their luster, beyond their shine... Azurite is one of those gems.",
    "shine": 8,
    "price": 110.50,
    "rarity": 7,
    "color": "#CCC",
    "faces": 14,
    "images": [
      "images/3/sledge3.jpg",
      "images/3/sledge3.1.jpg",
      "images/3/sledge3.2.jpg",
        "images/3/sledge3.3.jpg"
    ],
    "reviews": []
  },
  {
    "name": "Arctic Racer",
    "description": "Origin of the Bloodstone is unknown, hence its low value. It has a very high shine and 12 sides, however.",
    "shine": 9,
    "price": 22.90,
    "rarity": 6,
    "color": "#EEE",
    "faces": 12,
    "images": [
      "images/2/sledge2.jpg",
      "images/2/sledge2.1.jpg",
      "images/2/sledge2.2.jpg",
        "images/2/sledge2.3.jpg"
    ],
    "reviews": []
  },
  {
    "name": "Træ kælk",
    "description": "Zircon is our most coveted and sought after gem. You will pay much to be the proud owner of this gorgeous and high shine gem.",
    "shine": 70,
    "price": 1100,
    "rarity": 2,
    "color": "#000",
    "faces": 6,
    "images": [
      "Images/1/slegde1.jpg",
      "images/1/sledge1.1.jpg",
      "images/1/sledge1.2.jpg",
        "images/1/sledge1.3.jpg"
    ],
    "reviews": []
  },
    {
    "name": "Snow Power",
    "description": "Zircon is our most coveted and sought after gem. You will pay much to be the proud owner of this gorgeous and high shine gem.",
    "shine": 70,
    "price": 1100,
    "rarity": 2,
    "color": "#000",
    "faces": 6,
    "images": [
      "images/5/sledge5.jpg",
      "images/5/sledge5.1.jpg",
      "images/5/sledge5.2.jpg",
        "images/5/sledge5.3.jpg"
    ],
    "reviews": []
  }
]
